README.rst
setup.cfg
setup.py
dotsite/__init__.py
dotsite/darwin.py
dotsite/debuggers.py
dotsite/decorators.py
dotsite/dictionaries.py
dotsite/getch.py
dotsite/imports.py
dotsite/keyboard.py
dotsite/linux.py
dotsite/lists.py
dotsite/literals.py
dotsite/paths.py
dotsite/platforms.py
dotsite/pp.py
dotsite/randoms.py
dotsite/scripts.py
dotsite/splits.py
dotsite/streams.py
dotsite/term.py
dotsite/text_streams.py
dotsite/tracebacks.py
dotsite.egg-info/PKG-INFO
dotsite.egg-info/SOURCES.txt
dotsite.egg-info/dependency_links.txt
dotsite.egg-info/requires.txt
dotsite.egg-info/top_level.txt