Metadata-Version: 1.1
Name: dotsite
Version: 0.3.5
Summary: Python modules often used in dotjab, and elsewhere
Home-page: https://github.com/jalanb/dotsite
Author: J Alan Brogan
Author-email: github@al-got-rhythm.net
License: MIT License
Download-URL: https://github.com/jalanb/dotsite/tarball/v0.3.5
Platform: any
Classifier: Programming Language :: Python :: 2.7
Classifier: Development Status :: 1 - Planning
Classifier: Natural Language :: English
Classifier: Environment :: Console
Classifier: Intended Audience :: Developers
Classifier: License :: OSI Approved :: MIT License
Classifier: Operating System :: OS Independent
Classifier: Topic :: Software Development :: Build Tools
